flask_sweetalert2/__init__.py
flask_sweetalert2-11.23.0.20250916.dist-info/licenses/LICENSE.txt
flask_sweetalert2-11.23.0.20250916.dist-info/METADATA
flask_sweetalert2-11.23.0.20250916.dist-info/WHEEL
flask_sweetalert2-11.23.0.20250916.dist-info/top_level.txt
flask_sweetalert2-11.23.0.20250916.dist-info/RECORD
